Spider_Toolkit/__init__.py
Spider_Toolkit/spidertools.py
Spider_Toolkit/engine/Parameter_filtering_engine.py
Spider_Toolkit/engine/__init__.py
Spider_Toolkit/filtering/Download_byte_parameter_filtering.py
Spider_Toolkit/filtering/Download_m3u8_parameter_filtering.py
Spider_Toolkit/filtering/Open_js_parameter_filtering.py
Spider_Toolkit/filtering/Random_ua_parameter_filtering.py
Spider_Toolkit/filtering/Save_parameter_filtering.py
Spider_Toolkit/filtering/__init__.py
Spider_Toolkit/filtering/download_filtering/Download_byte_parameter_filtering.py
Spider_Toolkit/filtering/download_filtering/Download_m3u8_parameter_filtering.py
Spider_Toolkit/filtering/download_filtering/__init__.py
Spider_Toolkit/filtering/enc_dec_filtering/Base64_parameter_filtering.py
Spider_Toolkit/filtering/enc_dec_filtering/Md5_parameter_filtering.py
Spider_Toolkit/filtering/enc_dec_filtering/Sha_parameter_filtering.py
Spider_Toolkit/filtering/enc_dec_filtering/__init__.py
Spider_Toolkit/filtering/open_filtering/Open_js_parameter_filtering.py
Spider_Toolkit/filtering/open_filtering/__init__.py
Spider_Toolkit/filtering/random_filtering/Random_ua_parameter_filtering.py
Spider_Toolkit/filtering/random_filtering/__init__.py
Spider_Toolkit/filtering/save_filtering/Save_csv_parameter_filtering.py
Spider_Toolkit/filtering/save_filtering/Save_mongo_parameter_filtering.py
Spider_Toolkit/filtering/save_filtering/Save_mysql_parameter_filtering.py
Spider_Toolkit/filtering/save_filtering/Save_redis_parameter_filtering.py
Spider_Toolkit/filtering/save_filtering/Save_xlsx_parameter_filtering.py
Spider_Toolkit/filtering/save_filtering/__init__.py
Spider_Toolkit/tools/Download_byte.py
Spider_Toolkit/tools/Download_m3u8.py
Spider_Toolkit/tools/Open_js.py
Spider_Toolkit/tools/Random_ua.py
Spider_Toolkit/tools/Save.py
Spider_Toolkit/tools/__init__.py
Spider_Toolkit/tools/download/Download_byte.py
Spider_Toolkit/tools/download/Download_m3u8.py
Spider_Toolkit/tools/download/__init__.py
Spider_Toolkit-23.0.8.dist-info/LICENSE.txt
Spider_Toolkit-23.0.8.dist-info/METADATA
Spider_Toolkit-23.0.8.dist-info/WHEEL
Spider_Toolkit-23.0.8.dist-info/top_level.txt
Spider_Toolkit-23.0.8.dist-info/RECORD
